parsel/__init__.py
parsel/csstranslator.py
parsel/py.typed
parsel/selector.py
parsel/utils.py
parsel/xpathfuncs.py
parsel-1.9.0.dist-info/LICENSE
parsel-1.9.0.dist-info/METADATA
parsel-1.9.0.dist-info/WHEEL
parsel-1.9.0.dist-info/top_level.txt
parsel-1.9.0.dist-info/RECORD
