Metadata-Version: 2.1
Name: parsel
Version: 1.9.0
Summary: Parsel is a library to extract data from HTML and XML using XPath and CSS selectors
Home-page: https://github.com/scrapy/parsel
Author: Scrapy project
Author-email: info@scrapy.org
License: BSD
Keywords: parsel
Classifier: Development Status :: 5 - Production/Stable
Classifier: Intended Audience :: Developers
Classifier: License :: OSI Approved :: BSD License
Classifier: Natural Language :: English
Classifier: Topic :: Text Processing :: Markup
Classifier: Topic :: Text Processing :: Markup :: HTML
Classifier: Topic :: Text Processing :: Markup :: XML
Classifier: Programming Language :: Python :: 3
Classifier: Programming Language :: Python :: 3.8
Classifier: Programming Language :: Python :: 3.9
Classifier: Programming Language :: Python :: 3.10
Classifier: Programming Language :: Python :: 3.11
Classifier: Programming Language :: Python :: 3.12
Classifier: Programming Language :: Python :: Implementation :: CPython
Classifier: Programming Language :: Python :: Implementation :: PyPy
Requires-Python: >=3.8
License-File: LICENSE
Requires-Dist: cssselect>=1.2.0
Requires-Dist: jmespath
Requires-Dist: lxml
Requires-Dist: packaging
Requires-Dist: w3lib>=1.19.0
